django_minio_storage/__init__.py
django_minio_storage/storage.py
django_minio_storage_idtinc-1.1.0.dist-info/METADATA
django_minio_storage_idtinc-1.1.0.dist-info/WHEEL
django_minio_storage_idtinc-1.1.0.dist-info/top_level.txt
django_minio_storage_idtinc-1.1.0.dist-info/RECORD
