Metadata-Version: 2.4
Name: django-minio-storage-idtinc
Version: 1.1.0
Summary: Django Storage backend for MinIO
Author: Chuong Kieu Van
License: MIT
Project-URL: Homepage, https://github.com/vanchuongkieu/django-minio-storage
Requires-Python: >=3.9
Requires-Dist: django>=3.2
Requires-Dist: minio>=7.1.0
